modkr/__init__.py
modkr/__main__.py
modkr/adb_handler.py
modkr/config_manager.py
modkr/csv_handler.py
modkr/feature_handler.py
modkr/game_data_getter.py
modkr/helper.py
modkr/item.py
modkr/locale_handler.py
modkr/managed_item.py
modkr/parse_save.py
modkr/patcher.py
modkr/py.typed
modkr/root_handler.py
modkr/serialise_save.py
modkr/server_handler.py
modkr/tracker.py
modkr/updater.py
modkr/user_input_handler.py
modkr/__pycache__/__init__.cpython-311.pyc
modkr/__pycache__/__main__.cpython-311.pyc
modkr/__pycache__/adb_handler.cpython-311.pyc
modkr/__pycache__/config_manager.cpython-311.pyc
modkr/__pycache__/csv_handler.cpython-311.pyc
modkr/__pycache__/feature_handler.cpython-311.pyc
modkr/__pycache__/game_data_getter.cpython-311.pyc
modkr/__pycache__/helper.cpython-311.pyc
modkr/__pycache__/item.cpython-311.pyc
modkr/__pycache__/locale_handler.cpython-311.pyc
modkr/__pycache__/managed_item.cpython-311.pyc
modkr/__pycache__/parse_save.cpython-311.pyc
modkr/__pycache__/patcher.cpython-311.pyc
modkr/__pycache__/root_handler.cpython-311.pyc
modkr/__pycache__/serialise_save.cpython-311.pyc
modkr/__pycache__/server_handler.cpython-311.pyc
modkr/__pycache__/tracker.cpython-311.pyc
modkr/__pycache__/updater.cpython-311.pyc
modkr/__pycache__/user_input_handler.cpython-311.pyc
modkr/edits/__init__.py
modkr/edits/__pycache__/__init__.cpython-311.pyc
modkr/edits/basic/__init__.py
modkr/edits/basic/basic_items.py
modkr/edits/basic/catfruit.py
modkr/edits/basic/catseyes.py
modkr/edits/basic/ototo_base_mats.py
modkr/edits/basic/talent_orbs.py
modkr/edits/basic/talent_orbs_new.py
modkr/edits/basic/__pycache__/__init__.cpython-311.pyc
modkr/edits/basic/__pycache__/basic_items.cpython-311.pyc
modkr/edits/basic/__pycache__/catfruit.cpython-311.pyc
modkr/edits/basic/__pycache__/catseyes.cpython-311.pyc
modkr/edits/basic/__pycache__/ototo_base_mats.cpython-311.pyc
modkr/edits/basic/__pycache__/talent_orbs.cpython-311.pyc
modkr/edits/basic/__pycache__/talent_orbs_new.cpython-311.pyc
Shark_sac_Korean_editor-2.0.5.dist-info/METADATA
Shark_sac_Korean_editor-2.0.5.dist-info/WHEEL
Shark_sac_Korean_editor-2.0.5.dist-info/top_level.txt
Shark_sac_Korean_editor-2.0.5.dist-info/RECORD
